[
  {
    "incident_type": "abuse_allegation",
    "care_plan_updated": false,
    "attachments": [],
    "sub_category": null,
    "incident_date": "2026-04-08T12:33",
    "resolved_date": null,
    "description": "test",
    "cqc_notification_sent": false,
    "what_happened": "",
    "client_id": "69c0ff4222faba6a5b96513f",
    "safeguarding_type": [],
    "resolved_by": null,
    "staff_training_required": false,
    "staff_id": "",
    "lessons_learned": null,
    "police_involved": false,
    "risk_assessment_updated": false,
    "resolution_notes": null,
    "cqc_notification_date": null,
    "discovery_date": null,
    "outcome": null,
    "witnesses": [],
    "preventive_measures": [],
    "confidential": false,
    "severity": "medium",
    "reported_date": "2026-04-08T07:04:40.842Z",
    "family_notified_by": null,
    "family_notified": false,
    "review_completed": false,
    "reported_by_staff_id": "690d9c240a34ca4023dc316e",
    "cqc_reference": null,
    "location_detail": "Aries House, 60 Garmoyle Road, Liverpool, L15 3JH",
    "immediate_action_taken": "Test",
    "review_notes": null,
    "police_reference": null,
    "authorities_notified": [],
    "family_notification_date": null,
    "family_notification_method": null,
    "priority": "medium",
    "review_date": null,
    "injury_details": null,
    "is_safeguarding_concern": false,
    "investigation": null,
    "location": "Kailahun",
    "requires_notification_to_cqc": true,
    "visit_id": null,
    "incident_reference": "INC-20260408-0024",
    "status": "reported",
    "id": "69d5fe09f0e42cb595108adc",
    "created_date": "2026-04-08T07:04:41.180000",
    "updated_date": "2026-04-08T07:04:41.180000",
    "created_by_id": "690d9c240a34ca4023dc316e",
    "created_by": "vipin@appsandwebdevelopmentsolutions.com",
    "is_sample": false
  },
  {
    "incident_type": "abuse_allegation",
    "care_plan_updated": false,
    "attachments": [],
    "sub_category": null,
    "incident_date": "2026-04-08T12:27",
    "resolved_date": null,
    "description": "Test",
    "cqc_notification_sent": false,
    "what_happened": "",
    "client_id": "69c0ff4222faba6a5b96513f",
    "safeguarding_type": [
      "physical_abuse"
    ],
    "resolved_by": null,
    "staff_training_required": false,
    "staff_id": "",
    "lessons_learned": null,
    "police_involved": false,
    "risk_assessment_updated": false,
    "resolution_notes": null,
    "cqc_notification_date": null,
    "discovery_date": null,
    "outcome": null,
    "witnesses": [],
    "preventive_measures": [],
    "confidential": false,
    "severity": "low",
    "reported_date": "2026-04-08T07:02:57.149Z",
    "family_notified_by": null,
    "family_notified": false,
    "review_completed": false,
    "reported_by_staff_id": "690d9c240a34ca4023dc316e",
    "cqc_reference": null,
    "location_detail": "Aries House, 60 Garmoyle Road, Liverpool, L15 3JH",
    "immediate_action_taken": "teat",
    "review_notes": null,
    "police_reference": null,
    "authorities_notified": [],
    "family_notification_date": null,
    "family_notification_method": null,
    "priority": "medium",
    "review_date": null,
    "injury_details": null,
    "is_safeguarding_concern": true,
    "investigation": null,
    "location": "Kailahun",
    "requires_notification_to_cqc": true,
    "visit_id": null,
    "incident_reference": "INC-20260408-0023",
    "status": "reported",
    "id": "69d5fda1a1248a0b7b43acd8",
    "created_date": "2026-04-08T07:02:57.700000",
    "updated_date": "2026-04-08T07:02:57.700000",
    "created_by_id": "690d9c240a34ca4023dc316e",
    "created_by": "vipin@appsandwebdevelopmentsolutions.com",
    "is_sample": false
  },
  {
    "incident_type": "accident",
    "care_plan_updated": false,
    "attachments": [],
    "sub_category": null,
    "incident_date": "2026-02-28T14:20",
    "resolved_date": null,
    "description": "TEST",
    "cqc_notification_sent": false,
    "what_happened": "",
    "client_id": "694146c3b47d88b4898e0e0d",
    "safeguarding_type": [
      "physical_abuse",
      "sexual_abuse"
    ],
    "resolved_by": null,
    "staff_training_required": false,
    "staff_id": "",
    "lessons_learned": null,
    "police_involved": false,
    "risk_assessment_updated": false,
    "resolution_notes": null,
    "cqc_notification_date": null,
    "discovery_date": null,
    "outcome": null,
    "witnesses": [],
    "preventive_measures": [],
    "confidential": false,
    "severity": "critical",
    "reported_date": "2026-02-12T08:51:12.597Z",
    "family_notified_by": null,
    "family_notified": false,
    "review_completed": false,
    "reported_by_staff_id": "690d9c240a34ca4023dc316e",
    "cqc_reference": null,
    "location_detail": "",
    "immediate_action_taken": "TEST",
    "review_notes": null,
    "police_reference": null,
    "authorities_notified": [],
    "family_notification_date": null,
    "family_notification_method": null,
    "priority": "medium",
    "review_date": null,
    "injury_details": null,
    "is_safeguarding_concern": true,
    "investigation": null,
    "location": "italiy",
    "requires_notification_to_cqc": false,
    "visit_id": null,
    "incident_reference": "INC-20260212-0022",
    "status": "reported",
    "id": "698d9480d3bd4ea95661fcb5",
    "created_date": "2026-02-12T08:51:12.471000",
    "updated_date": "2026-02-12T08:51:12.471000",
    "created_by_id": "690d9c240a34ca4023dc316e",
    "created_by": "vipin@appsandwebdevelopmentsolutions.com",
    "is_sample": false
  },
  {
    "incident_reference": "INC-20260210-0021",
    "incident_type": "accident",
    "sub_category": null,
    "severity": "medium",
    "is_safeguarding_concern": false,
    "safeguarding_type": [],
    "client_id": "694146c3b47d88b4898e0e0d",
    "staff_id": "",
    "reported_by_staff_id": "690d9c240a34ca4023dc316e",
    "visit_id": null,
    "incident_date": "2026-02-10T16:59",
    "reported_date": "2026-02-10T11:30:02.885Z",
    "discovery_date": null,
    "location": "Australia",
    "location_detail": "Test",
    "description": "Test",
    "what_happened": "",
    "immediate_action_taken": "ambulance called",
    "injury_details": null,
    "witnesses": [],
    "family_notified": false,
    "family_notification_date": null,
    "family_notification_method": null,
    "family_notified_by": null,
    "authorities_notified": [],
    "status": "reported",
    "investigation": null,
    "outcome": null,
    "resolution_notes": null,
    "resolved_by": null,
    "resolved_date": null,
    "lessons_learned": null,
    "preventive_measures": [],
    "risk_assessment_updated": false,
    "care_plan_updated": false,
    "staff_training_required": false,
    "review_date": null,
    "review_completed": false,
    "review_notes": null,
    "attachments": [],
    "priority": "medium",
    "requires_notification_to_cqc": false,
    "cqc_notification_sent": false,
    "cqc_notification_date": null,
    "cqc_reference": null,
    "police_involved": false,
    "police_reference": null,
    "confidential": false,
    "id": "698b16bbc5a243bceddf1a9b",
    "created_date": "2026-02-10T11:30:03.059000",
    "updated_date": "2026-02-10T11:30:03.059000",
    "created_by_id": "690d9c240a34ca4023dc316e",
    "created_by": "vipin@appsandwebdevelopmentsolutions.com",
    "is_sample": false
  },
  {
    "incident_reference": "INC-20260210-0020",
    "incident_type": "medication_error",
    "sub_category": null,
    "severity": "medium",
    "is_safeguarding_concern": false,
    "safeguarding_type": [],
    "client_id": "694146c3b47d88b4898e0e0d",
    "staff_id": "",
    "reported_by_staff_id": "690d9c240a34ca4023dc316e",
    "visit_id": null,
    "incident_date": "2026-02-10T16:57",
    "reported_date": "2026-02-10T11:27:32.264Z",
    "discovery_date": null,
    "location": "Noida",
    "location_detail": "Test",
    "description": "Test",
    "what_happened": "",
    "immediate_action_taken": "Test",
    "injury_details": null,
    "witnesses": [],
    "family_notified": false,
    "family_notification_date": null,
    "family_notification_method": null,
    "family_notified_by": null,
    "authorities_notified": [],
    "status": "reported",
    "investigation": null,
    "outcome": null,
    "resolution_notes": null,
    "resolved_by": null,
    "resolved_date": null,
    "lessons_learned": null,
    "preventive_measures": [],
    "risk_assessment_updated": false,
    "care_plan_updated": false,
    "staff_training_required": false,
    "review_date": null,
    "review_completed": false,
    "review_notes": null,
    "attachments": [],
    "priority": "medium",
    "requires_notification_to_cqc": false,
    "cqc_notification_sent": false,
    "cqc_notification_date": null,
    "cqc_reference": null,
    "police_involved": false,
    "police_reference": null,
    "confidential": false,
    "id": "698b1624fb0695cc443a05da",
    "created_date": "2026-02-10T11:27:32.779000",
    "updated_date": "2026-02-10T11:27:32.779000",
    "created_by_id": "690d9c240a34ca4023dc316e",
    "created_by": "vipin@appsandwebdevelopmentsolutions.com",
    "is_sample": false
  },
  {
    "incident_reference": "INC-20260207-0019",
    "incident_type": "accident",
    "sub_category": null,
    "severity": "medium",
    "is_safeguarding_concern": false,
    "safeguarding_type": [],
    "client_id": "69381b467065d8ef6cf20ed0",
    "staff_id": "",
    "reported_by_staff_id": "690d9c240a34ca4023dc316e",
    "visit_id": null,
    "incident_date": "2026-02-07T12:18",
    "reported_date": "2026-02-07T06:48:38.863Z",
    "discovery_date": null,
    "location": "Wocanda",
    "location_detail": "sdf",
    "description": "sadf",
    "what_happened": "",
    "immediate_action_taken": "asdf",
    "injury_details": null,
    "witnesses": [],
    "family_notified": false,
    "family_notification_date": null,
    "family_notification_method": null,
    "family_notified_by": null,
    "authorities_notified": [],
    "status": "reported",
    "investigation": null,
    "outcome": null,
    "resolution_notes": null,
    "resolved_by": null,
    "resolved_date": null,
    "lessons_learned": null,
    "preventive_measures": [],
    "risk_assessment_updated": false,
    "care_plan_updated": false,
    "staff_training_required": false,
    "review_date": null,
    "review_completed": false,
    "review_notes": null,
    "attachments": [],
    "priority": "medium",
    "requires_notification_to_cqc": false,
    "cqc_notification_sent": false,
    "cqc_notification_date": null,
    "cqc_reference": null,
    "police_involved": false,
    "police_reference": null,
    "confidential": false,
    "id": "6986e047a92767156e349e61",
    "created_date": "2026-02-07T06:48:39.384000",
    "updated_date": "2026-02-07T06:48:39.384000",
    "created_by_id": "690d9c240a34ca4023dc316e",
    "created_by": "vipin@appsandwebdevelopmentsolutions.com",
    "is_sample": false
  },
  {
    "incident_reference": "INC-20260207-0018",
    "incident_type": "safeguarding_concern",
    "sub_category": null,
    "severity": "medium",
    "is_safeguarding_concern": false,
    "safeguarding_type": [],
    "client_id": "6909e7f22522fdf33fb86ec7",
    "staff_id": "",
    "reported_by_staff_id": "690d9c240a34ca4023dc316e",
    "visit_id": null,
    "incident_date": "2026-02-07T12:04",
    "reported_date": "2026-02-07T06:34:40.583Z",
    "discovery_date": null,
    "location": "Wocanda",
    "location_detail": "test",
    "description": "test",
    "what_happened": "",
    "immediate_action_taken": "test",
    "injury_details": null,
    "witnesses": [],
    "family_notified": false,
    "family_notification_date": null,
    "family_notification_method": null,
    "family_notified_by": null,
    "authorities_notified": [],
    "status": "reported",
    "investigation": null,
    "outcome": null,
    "resolution_notes": null,
    "resolved_by": null,
    "resolved_date": null,
    "lessons_learned": null,
    "preventive_measures": [],
    "risk_assessment_updated": false,
    "care_plan_updated": false,
    "staff_training_required": false,
    "review_date": null,
    "review_completed": false,
    "review_notes": null,
    "attachments": [],
    "priority": "medium",
    "requires_notification_to_cqc": false,
    "cqc_notification_sent": false,
    "cqc_notification_date": null,
    "cqc_reference": null,
    "police_involved": false,
    "police_reference": null,
    "confidential": false,
    "id": "6986dd01ba73d063beffed2c",
    "created_date": "2026-02-07T06:34:41.103000",
    "updated_date": "2026-02-07T06:34:41.103000",
    "created_by_id": "690d9c240a34ca4023dc316e",
    "created_by": "vipin@appsandwebdevelopmentsolutions.com",
    "is_sample": false
  },
  {
    "incident_reference": "INC-20260206-0017",
    "incident_type": "accident",
    "sub_category": null,
    "severity": "critical",
    "is_safeguarding_concern": true,
    "safeguarding_type": [],
    "client_id": "694146c3b47d88b4898e0e0d",
    "staff_id": "",
    "reported_by_staff_id": "690d9c240a34ca4023dc316e",
    "visit_id": null,
    "incident_date": "2026-02-06T14:47",
    "reported_date": "2026-02-06T09:18:25.009Z",
    "discovery_date": null,
    "location": "Wocanda",
    "location_detail": "wocanda root",
    "description": "All with SAFEGUARDING Happned",
    "what_happened": "",
    "immediate_action_taken": "All with SAFEGUARDING Action",
    "injury_details": null,
    "witnesses": [],
    "family_notified": true,
    "family_notification_date": null,
    "family_notification_method": null,
    "family_notified_by": null,
    "authorities_notified": [],
    "status": "reported",
    "investigation": null,
    "outcome": null,
    "resolution_notes": null,
    "resolved_by": null,
    "resolved_date": null,
    "lessons_learned": null,
    "preventive_measures": [],
    "risk_assessment_updated": false,
    "care_plan_updated": false,
    "staff_training_required": false,
    "review_date": null,
    "review_completed": false,
    "review_notes": null,
    "attachments": [],
    "priority": "medium",
    "requires_notification_to_cqc": true,
    "cqc_notification_sent": false,
    "cqc_notification_date": null,
    "cqc_reference": null,
    "police_involved": true,
    "police_reference": null,
    "confidential": false,
    "id": "6985b1e1b8d963a32486e374",
    "created_date": "2026-02-06T09:18:25.651000",
    "updated_date": "2026-02-06T09:18:25.651000",
    "created_by_id": "690d9c240a34ca4023dc316e",
    "created_by": "vipin@appsandwebdevelopmentsolutions.com",
    "is_sample": false
  },
  {
    "incident_reference": "INC-20260206-0016",
    "incident_type": "accident",
    "sub_category": null,
    "severity": "critical",
    "is_safeguarding_concern": true,
    "safeguarding_type": [
      "physical_abuse"
    ],
    "client_id": "694146c3b47d88b4898e0e0d",
    "staff_id": "",
    "reported_by_staff_id": "690d9c240a34ca4023dc316e",
    "visit_id": null,
    "incident_date": "2026-02-06T14:45",
    "reported_date": "2026-02-06T09:16:43.754Z",
    "discovery_date": null,
    "location": "Wocanda",
    "location_detail": "wocanda root",
    "description": "only SAFEGUARDING Happened",
    "what_happened": "",
    "immediate_action_taken": "only SAFEGUARDING action",
    "injury_details": null,
    "witnesses": [],
    "family_notified": false,
    "family_notification_date": null,
    "family_notification_method": null,
    "family_notified_by": null,
    "authorities_notified": [],
    "status": "reported",
    "investigation": null,
    "outcome": null,
    "resolution_notes": null,
    "resolved_by": null,
    "resolved_date": null,
    "lessons_learned": null,
    "preventive_measures": [],
    "risk_assessment_updated": false,
    "care_plan_updated": false,
    "staff_training_required": false,
    "review_date": null,
    "review_completed": false,
    "review_notes": null,
    "attachments": [],
    "priority": "medium",
    "requires_notification_to_cqc": false,
    "cqc_notification_sent": false,
    "cqc_notification_date": null,
    "cqc_reference": null,
    "police_involved": false,
    "police_reference": null,
    "confidential": false,
    "id": "6985b17beb327a6177c06fcb",
    "created_date": "2026-02-06T09:16:43.757000",
    "updated_date": "2026-02-06T09:16:43.757000",
    "created_by_id": "690d9c240a34ca4023dc316e",
    "created_by": "vipin@appsandwebdevelopmentsolutions.com",
    "is_sample": false
  },
  {
    "incident_reference": "INC-20260206-0015",
    "incident_type": "accident",
    "sub_category": null,
    "severity": "medium",
    "is_safeguarding_concern": false,
    "safeguarding_type": [],
    "client_id": "694146c3b47d88b4898e0e0d",
    "staff_id": "",
    "reported_by_staff_id": "690d9c240a34ca4023dc316e",
    "visit_id": null,
    "incident_date": "2026-02-06T14:44",
    "reported_date": "2026-02-06T09:15:03.597Z",
    "discovery_date": null,
    "location": "Wocanda",
    "location_detail": "",
    "description": "Police Happened",
    "what_happened": "",
    "immediate_action_taken": "Police Action",
    "injury_details": null,
    "witnesses": [],
    "family_notified": false,
    "family_notification_date": null,
    "family_notification_method": null,
    "family_notified_by": null,
    "authorities_notified": [],
    "status": "reported",
    "investigation": null,
    "outcome": null,
    "resolution_notes": null,
    "resolved_by": null,
    "resolved_date": null,
    "lessons_learned": null,
    "preventive_measures": [],
    "risk_assessment_updated": false,
    "care_plan_updated": false,
    "staff_training_required": false,
    "review_date": null,
    "review_completed": false,
    "review_notes": null,
    "attachments": [],
    "priority": "medium",
    "requires_notification_to_cqc": false,
    "cqc_notification_sent": false,
    "cqc_notification_date": null,
    "cqc_reference": null,
    "police_involved": true,
    "police_reference": null,
    "confidential": false,
    "id": "6985b117e305a4f00e4e71ec",
    "created_date": "2026-02-06T09:15:03.608000",
    "updated_date": "2026-02-06T09:15:03.608000",
    "created_by_id": "690d9c240a34ca4023dc316e",
    "created_by": "vipin@appsandwebdevelopmentsolutions.com",
    "is_sample": false
  },
  {
    "incident_reference": "INC-20260206-0014",
    "incident_type": "accident",
    "sub_category": null,
    "severity": "medium",
    "is_safeguarding_concern": false,
    "safeguarding_type": [],
    "client_id": "694146c3b47d88b4898e0e0d",
    "staff_id": "",
    "reported_by_staff_id": "690d9c240a34ca4023dc316e",
    "visit_id": null,
    "incident_date": "2026-02-06T14:43",
    "reported_date": "2026-02-06T09:13:47.699Z",
    "discovery_date": null,
    "location": "Wocanda",
    "location_detail": "wocanda root",
    "description": "COC Happened",
    "what_happened": "",
    "immediate_action_taken": "COC Action",
    "injury_details": null,
    "witnesses": [],
    "family_notified": false,
    "family_notification_date": null,
    "family_notification_method": null,
    "family_notified_by": null,
    "authorities_notified": [],
    "status": "reported",
    "investigation": null,
    "outcome": null,
    "resolution_notes": null,
    "resolved_by": null,
    "resolved_date": null,
    "lessons_learned": null,
    "preventive_measures": [],
    "risk_assessment_updated": false,
    "care_plan_updated": false,
    "staff_training_required": false,
    "review_date": null,
    "review_completed": false,
    "review_notes": null,
    "attachments": [],
    "priority": "medium",
    "requires_notification_to_cqc": true,
    "cqc_notification_sent": false,
    "cqc_notification_date": null,
    "cqc_reference": null,
    "police_involved": false,
    "police_reference": null,
    "confidential": false,
    "id": "6985b0cbaad2fe353ed0716c",
    "created_date": "2026-02-06T09:13:47.718000",
    "updated_date": "2026-02-06T09:13:47.718000",
    "created_by_id": "690d9c240a34ca4023dc316e",
    "created_by": "vipin@appsandwebdevelopmentsolutions.com",
    "is_sample": false
  },
  {
    "incident_reference": "INC-20260206-0013",
    "incident_type": "accident",
    "sub_category": null,
    "severity": "medium",
    "is_safeguarding_concern": false,
    "safeguarding_type": [],
    "client_id": "694146c3b47d88b4898e0e0d",
    "staff_id": "",
    "reported_by_staff_id": "690d9c240a34ca4023dc316e",
    "visit_id": null,
    "incident_date": "2026-02-06T14:40",
    "reported_date": "2026-02-06T09:11:48.797Z",
    "discovery_date": null,
    "location": "Wocanda",
    "location_detail": "wocanda root",
    "description": "Family Happend",
    "what_happened": "",
    "immediate_action_taken": "Faimily action",
    "injury_details": null,
    "witnesses": [],
    "family_notified": true,
    "family_notification_date": null,
    "family_notification_method": null,
    "family_notified_by": null,
    "authorities_notified": [],
    "status": "reported",
    "investigation": null,
    "outcome": null,
    "resolution_notes": null,
    "resolved_by": null,
    "resolved_date": null,
    "lessons_learned": null,
    "preventive_measures": [],
    "risk_assessment_updated": false,
    "care_plan_updated": false,
    "staff_training_required": false,
    "review_date": null,
    "review_completed": false,
    "review_notes": null,
    "attachments": [],
    "priority": "medium",
    "requires_notification_to_cqc": false,
    "cqc_notification_sent": false,
    "cqc_notification_date": null,
    "cqc_reference": null,
    "police_involved": false,
    "police_reference": null,
    "confidential": false,
    "id": "6985b05520a6469fbf7a3e73",
    "created_date": "2026-02-06T09:11:49.049000",
    "updated_date": "2026-02-06T09:11:49.049000",
    "created_by_id": "690d9c240a34ca4023dc316e",
    "created_by": "vipin@appsandwebdevelopmentsolutions.com",
    "is_sample": false
  },
  {
    "incident_reference": "INC-20260206-0012",
    "incident_type": "accident",
    "sub_category": null,
    "severity": "low",
    "is_safeguarding_concern": false,
    "safeguarding_type": [],
    "client_id": "6909e7f22522fdf33fb86ec7",
    "staff_id": "",
    "reported_by_staff_id": "690d9c240a34ca4023dc316e",
    "visit_id": null,
    "incident_date": "2026-02-06T12:28",
    "reported_date": "2026-02-06T06:58:36.030Z",
    "discovery_date": null,
    "location": "Wocanda",
    "location_detail": "wocanda root",
    "description": "dsfg",
    "what_happened": "",
    "immediate_action_taken": "dfgh",
    "injury_details": null,
    "witnesses": [],
    "family_notified": false,
    "family_notification_date": null,
    "family_notification_method": null,
    "family_notified_by": null,
    "authorities_notified": [],
    "status": "reported",
    "investigation": null,
    "outcome": null,
    "resolution_notes": null,
    "resolved_by": null,
    "resolved_date": null,
    "lessons_learned": null,
    "preventive_measures": [],
    "risk_assessment_updated": false,
    "care_plan_updated": false,
    "staff_training_required": false,
    "review_date": null,
    "review_completed": false,
    "review_notes": null,
    "attachments": [],
    "priority": "medium",
    "requires_notification_to_cqc": true,
    "cqc_notification_sent": false,
    "cqc_notification_date": null,
    "cqc_reference": null,
    "police_involved": false,
    "police_reference": null,
    "confidential": false,
    "id": "6985911ca5f597174f49c6be",
    "created_date": "2026-02-06T06:58:36.615000",
    "updated_date": "2026-02-06T06:58:36.615000",
    "created_by_id": "690d9c240a34ca4023dc316e",
    "created_by": "vipin@appsandwebdevelopmentsolutions.com",
    "is_sample": false
  },
  {
    "incident_type": "safeguarding_concern",
    "care_plan_updated": false,
    "attachments": [],
    "sub_category": null,
    "incident_date": "2026-02-05T16:28",
    "resolved_date": null,
    "description": "Test Happened",
    "cqc_notification_sent": false,
    "what_happened": "",
    "client_id": "694146c3b47d88b4898e0e0d",
    "safeguarding_type": [],
    "resolved_by": null,
    "staff_training_required": false,
    "staff_id": "",
    "lessons_learned": null,
    "police_involved": true,
    "risk_assessment_updated": false,
    "resolution_notes": null,
    "cqc_notification_date": null,
    "discovery_date": null,
    "outcome": null,
    "witnesses": [],
    "preventive_measures": [],
    "confidential": false,
    "severity": "medium",
    "reported_date": "2026-02-05T10:59:17.121Z",
    "family_notified_by": null,
    "family_notified": true,
    "review_completed": false,
    "reported_by_staff_id": "690d9c240a34ca4023dc316e",
    "cqc_reference": null,
    "location_detail": "wocanda root",
    "immediate_action_taken": "Test Action",
    "review_notes": null,
    "police_reference": null,
    "authorities_notified": [],
    "family_notification_date": null,
    "family_notification_method": null,
    "priority": "medium",
    "review_date": null,
    "injury_details": null,
    "is_safeguarding_concern": false,
    "investigation": null,
    "location": "Wocanda",
    "requires_notification_to_cqc": true,
    "visit_id": null,
    "incident_reference": "INC-20260205-0011",
    "status": "reported",
    "id": "69847805d4a8c88d0296b064",
    "created_date": "2026-02-05T10:59:17.394000",
    "updated_date": "2026-02-05T10:59:17.394000",
    "created_by_id": "690d9c240a34ca4023dc316e",
    "created_by": "vipin@appsandwebdevelopmentsolutions.com",
    "is_sample": false
  },
  {
    "incident_type": "accident",
    "care_plan_updated": false,
    "attachments": [],
    "sub_category": null,
    "incident_date": "2026-02-04T17:46",
    "resolved_date": null,
    "description": "tttttttttttttttt",
    "cqc_notification_sent": false,
    "what_happened": "",
    "client_id": "694146c3b47d88b4898e0e0d",
    "safeguarding_type": [],
    "resolved_by": null,
    "staff_training_required": false,
    "staff_id": "",
    "lessons_learned": null,
    "police_involved": false,
    "risk_assessment_updated": false,
    "resolution_notes": null,
    "cqc_notification_date": null,
    "discovery_date": null,
    "outcome": null,
    "witnesses": [],
    "preventive_measures": [],
    "confidential": false,
    "severity": "critical",
    "reported_date": "2026-02-04T12:16:38.335Z",
    "family_notified_by": null,
    "family_notified": false,
    "review_completed": false,
    "reported_by_staff_id": "690d9c240a34ca4023dc316e",
    "cqc_reference": null,
    "location_detail": "wocanda root",
    "immediate_action_taken": "rrrrrrrrrrrrrrrrrrrr",
    "review_notes": null,
    "police_reference": null,
    "authorities_notified": [],
    "family_notification_date": null,
    "family_notification_method": null,
    "priority": "medium",
    "review_date": null,
    "injury_details": null,
    "is_safeguarding_concern": true,
    "investigation": null,
    "location": "Wocanda",
    "requires_notification_to_cqc": false,
    "visit_id": null,
    "incident_reference": "INC-20260204-0010",
    "status": "reported",
    "id": "698338a51b32170d2828bfd4",
    "created_date": "2026-02-04T12:16:37.810000",
    "updated_date": "2026-02-04T12:16:37.810000",
    "created_by_id": "690d9c240a34ca4023dc316e",
    "created_by": "vipin@appsandwebdevelopmentsolutions.com",
    "is_sample": false
  },
  {
    "incident_type": "accident",
    "care_plan_updated": false,
    "attachments": [],
    "sub_category": null,
    "incident_date": "2026-02-04T17:31",
    "resolved_date": null,
    "description": "test",
    "cqc_notification_sent": false,
    "what_happened": "",
    "client_id": "694146c3b47d88b4898e0e0d",
    "safeguarding_type": [],
    "resolved_by": null,
    "staff_training_required": false,
    "staff_id": "",
    "lessons_learned": null,
    "police_involved": false,
    "risk_assessment_updated": false,
    "resolution_notes": null,
    "cqc_notification_date": null,
    "discovery_date": null,
    "outcome": null,
    "witnesses": [],
    "preventive_measures": [],
    "confidential": false,
    "severity": "critical",
    "reported_date": "2026-02-04T12:12:07.560Z",
    "family_notified_by": null,
    "family_notified": false,
    "review_completed": false,
    "reported_by_staff_id": "690d9c240a34ca4023dc316e",
    "cqc_reference": null,
    "location_detail": "test",
    "immediate_action_taken": "test",
    "review_notes": null,
    "police_reference": null,
    "authorities_notified": [],
    "family_notification_date": null,
    "family_notification_method": null,
    "priority": "medium",
    "review_date": null,
    "injury_details": null,
    "is_safeguarding_concern": true,
    "investigation": null,
    "location": "Noida",
    "requires_notification_to_cqc": false,
    "visit_id": null,
    "incident_reference": "INC-20260204-0009",
    "status": "reported",
    "id": "6983379899cb7936c4ba4e4a",
    "created_date": "2026-02-04T12:12:08.776000",
    "updated_date": "2026-02-04T12:12:08.776000",
    "created_by_id": "690d9c240a34ca4023dc316e",
    "created_by": "vipin@appsandwebdevelopmentsolutions.com",
    "is_sample": false
  },
  {
    "incident_type": "injury",
    "care_plan_updated": false,
    "attachments": [],
    "sub_category": null,
    "incident_date": "2026-02-03T10:11",
    "resolved_date": null,
    "description": "test",
    "cqc_notification_sent": false,
    "what_happened": "",
    "client_id": "6909e7f22522fdf33fb86ec7",
    "safeguarding_type": [],
    "resolved_by": null,
    "staff_training_required": false,
    "staff_id": "",
    "lessons_learned": null,
    "police_involved": false,
    "risk_assessment_updated": false,
    "resolution_notes": null,
    "cqc_notification_date": null,
    "discovery_date": null,
    "outcome": null,
    "witnesses": [],
    "preventive_measures": [],
    "confidential": false,
    "severity": "critical",
    "reported_date": "2026-02-03T04:44:37.575Z",
    "family_notified_by": null,
    "family_notified": false,
    "review_completed": false,
    "reported_by_staff_id": "690d9c240a34ca4023dc316e",
    "cqc_reference": null,
    "location_detail": "",
    "immediate_action_taken": "test",
    "review_notes": null,
    "police_reference": null,
    "authorities_notified": [],
    "family_notification_date": null,
    "family_notification_method": null,
    "priority": "medium",
    "review_date": null,
    "injury_details": null,
    "is_safeguarding_concern": false,
    "investigation": null,
    "location": "Noida",
    "requires_notification_to_cqc": false,
    "visit_id": null,
    "incident_reference": "INC-20260203-0008",
    "status": "reported",
    "id": "69817d36dc6bbee0ab481bc7",
    "created_date": "2026-02-03T04:44:38.026000",
    "updated_date": "2026-02-03T04:44:38.026000",
    "created_by_id": "690d9c240a34ca4023dc316e",
    "created_by": "vipin@appsandwebdevelopmentsolutions.com",
    "is_sample": false
  },
  {
    "incident_type": "fall",
    "care_plan_updated": false,
    "attachments": [],
    "sub_category": null,
    "incident_date": "2026-01-14T14:35",
    "resolved_date": null,
    "description": "asdasdasdasd",
    "cqc_notification_sent": false,
    "what_happened": "",
    "client_id": "69381b467065d8ef6cf20ed0",
    "safeguarding_type": [
      "physical_abuse",
      "emotional_abuse",
      "sexual_abuse",
      "financial_abuse",
      "discriminatory_abuse",
      "modern_slavery",
      "organisational_abuse",
      "neglect",
      "domestic_abuse",
      "self_neglect"
    ],
    "resolved_by": null,
    "staff_training_required": false,
    "staff_id": "",
    "lessons_learned": "",
    "police_involved": true,
    "risk_assessment_updated": false,
    "resolution_notes": "",
    "cqc_notification_date": null,
    "discovery_date": null,
    "outcome": null,
    "witnesses": [],
    "preventive_measures": [],
    "confidential": false,
    "severity": "critical",
    "reported_date": "2026-01-14T09:06:33.977Z",
    "family_notified_by": null,
    "family_notified": true,
    "review_completed": false,
    "reported_by_staff_id": "69578dc85ffbccbf237c772e",
    "cqc_reference": null,
    "location_detail": "gautam budh nagar",
    "immediate_action_taken": "asdasda",
    "review_notes": null,
    "police_reference": null,
    "authorities_notified": [],
    "family_notification_date": null,
    "family_notification_method": null,
    "priority": "medium",
    "review_date": null,
    "injury_details": null,
    "is_safeguarding_concern": true,
    "investigation": {
      "investigation_completion_date": null,
      "investigator_staff_id": null,
      "investigation_start_date": null,
      "findings": "",
      "root_cause": null,
      "contributing_factors": []
    },
    "location": "noida",
    "requires_notification_to_cqc": true,
    "visit_id": null,
    "incident_reference": "INC-20260114-0007",
    "status": "under_investigation",
    "id": "69675c9a212d102989a27ddb",
    "created_date": "2026-01-14T09:06:34.732000",
    "updated_date": "2026-01-29T15:17:36.093000",
    "created_by_id": "69578dc85ffbccbf237c772e",
    "created_by": "mobappssolutions169@gmail.com",
    "is_sample": false
  },
  {
    "incident_reference": "INC-20260114-0006",
    "incident_type": "fall",
    "sub_category": null,
    "severity": "critical",
    "is_safeguarding_concern": true,
    "safeguarding_type": [
      "physical_abuse",
      "emotional_abuse",
      "sexual_abuse",
      "financial_abuse",
      "discriminatory_abuse",
      "modern_slavery",
      "organisational_abuse",
      "neglect",
      "domestic_abuse",
      "self_neglect"
    ],
    "client_id": "69381b467065d8ef6cf20ed0",
    "staff_id": "",
    "reported_by_staff_id": "69578dc85ffbccbf237c772e",
    "visit_id": null,
    "incident_date": "2026-01-14T14:35",
    "reported_date": "2026-01-14T09:06:19.706Z",
    "discovery_date": null,
    "location": "noida",
    "location_detail": "gautam budh nagar",
    "description": "asdasdasdasd",
    "what_happened": "",
    "immediate_action_taken": "asdasda",
    "injury_details": null,
    "witnesses": [],
    "family_notified": true,
    "family_notification_date": null,
    "family_notification_method": null,
    "family_notified_by": null,
    "authorities_notified": [],
    "status": "reported",
    "investigation": null,
    "outcome": null,
    "resolution_notes": null,
    "resolved_by": null,
    "resolved_date": null,
    "lessons_learned": null,
    "preventive_measures": [],
    "risk_assessment_updated": false,
    "care_plan_updated": false,
    "staff_training_required": false,
    "review_date": null,
    "review_completed": false,
    "review_notes": null,
    "attachments": [],
    "priority": "medium",
    "requires_notification_to_cqc": true,
    "cqc_notification_sent": false,
    "cqc_notification_date": null,
    "cqc_reference": null,
    "police_involved": true,
    "police_reference": null,
    "confidential": false,
    "id": "69675c8c4e47fcba4ef95802",
    "created_date": "2026-01-14T09:06:20.448000",
    "updated_date": "2026-01-14T09:06:20.448000",
    "created_by_id": "69578dc85ffbccbf237c772e",
    "created_by": "mobappssolutions169@gmail.com",
    "is_sample": false
  },
  {
    "incident_reference": "INC-20260114-0005",
    "incident_type": "fall",
    "sub_category": null,
    "severity": "high",
    "is_safeguarding_concern": false,
    "safeguarding_type": [],
    "client_id": "69381b467065d8ef6cf20ed0",
    "staff_id": "",
    "reported_by_staff_id": "69578dc85ffbccbf237c772e",
    "visit_id": null,
    "incident_date": "2026-01-14T14:35",
    "reported_date": "2026-01-14T09:06:03.590Z",
    "discovery_date": null,
    "location": "noida",
    "location_detail": "gautam budh nagar",
    "description": "asdasdasdasd",
    "what_happened": "",
    "immediate_action_taken": "asdasda",
    "injury_details": null,
    "witnesses": [],
    "family_notified": true,
    "family_notification_date": null,
    "family_notification_method": null,
    "family_notified_by": null,
    "authorities_notified": [],
    "status": "reported",
    "investigation": null,
    "outcome": null,
    "resolution_notes": null,
    "resolved_by": null,
    "resolved_date": null,
    "lessons_learned": null,
    "preventive_measures": [],
    "risk_assessment_updated": false,
    "care_plan_updated": false,
    "staff_training_required": false,
    "review_date": null,
    "review_completed": false,
    "review_notes": null,
    "attachments": [],
    "priority": "medium",
    "requires_notification_to_cqc": true,
    "cqc_notification_sent": false,
    "cqc_notification_date": null,
    "cqc_reference": null,
    "police_involved": true,
    "police_reference": null,
    "confidential": false,
    "id": "69675c7ccb785a76ec2d6cf2",
    "created_date": "2026-01-14T09:06:04.677000",
    "updated_date": "2026-01-14T09:06:04.677000",
    "created_by_id": "69578dc85ffbccbf237c772e",
    "created_by": "mobappssolutions169@gmail.com",
    "is_sample": false
  },
  {
    "incident_reference": "INC-20260114-0004",
    "incident_type": "medication_error",
    "sub_category": null,
    "severity": "medium",
    "is_safeguarding_concern": false,
    "safeguarding_type": [],
    "client_id": "6925cd17c40f16dba6560a3a",
    "staff_id": "",
    "reported_by_staff_id": "69578dc85ffbccbf237c772e",
    "visit_id": null,
    "incident_date": "2026-01-14T14:19",
    "reported_date": "2026-01-14T08:50:35.962Z",
    "discovery_date": null,
    "location": "noida",
    "location_detail": "gautam budh nagar",
    "description": "nothing ahppen",
    "what_happened": "",
    "immediate_action_taken": "no need any action",
    "injury_details": null,
    "witnesses": [],
    "family_notified": true,
    "family_notification_date": null,
    "family_notification_method": null,
    "family_notified_by": null,
    "authorities_notified": [],
    "status": "reported",
    "investigation": null,
    "outcome": null,
    "resolution_notes": null,
    "resolved_by": null,
    "resolved_date": null,
    "lessons_learned": null,
    "preventive_measures": [],
    "risk_assessment_updated": false,
    "care_plan_updated": false,
    "staff_training_required": false,
    "review_date": null,
    "review_completed": false,
    "review_notes": null,
    "attachments": [],
    "priority": "medium",
    "requires_notification_to_cqc": true,
    "cqc_notification_sent": false,
    "cqc_notification_date": null,
    "cqc_reference": null,
    "police_involved": true,
    "police_reference": null,
    "confidential": false,
    "id": "696758dcb7e871976d008545",
    "created_date": "2026-01-14T08:50:36.749000",
    "updated_date": "2026-01-14T08:50:36.749000",
    "created_by_id": "69578dc85ffbccbf237c772e",
    "created_by": "mobappssolutions169@gmail.com",
    "is_sample": false
  },
  {
    "incident_reference": "INC-20260114-0003",
    "incident_type": "medication_error",
    "sub_category": null,
    "severity": "medium",
    "is_safeguarding_concern": false,
    "safeguarding_type": [],
    "client_id": "6925cd17c40f16dba6560a3a",
    "staff_id": "",
    "reported_by_staff_id": "69578dc85ffbccbf237c772e",
    "visit_id": null,
    "incident_date": "2026-01-14T14:19",
    "reported_date": "2026-01-14T08:50:30.582Z",
    "discovery_date": null,
    "location": "noida",
    "location_detail": "gautam budh nagar",
    "description": "nothing ahppen",
    "what_happened": "",
    "immediate_action_taken": "no need any action",
    "injury_details": null,
    "witnesses": [],
    "family_notified": true,
    "family_notification_date": null,
    "family_notification_method": null,
    "family_notified_by": null,
    "authorities_notified": [],
    "status": "reported",
    "investigation": null,
    "outcome": null,
    "resolution_notes": null,
    "resolved_by": null,
    "resolved_date": null,
    "lessons_learned": null,
    "preventive_measures": [],
    "risk_assessment_updated": false,
    "care_plan_updated": false,
    "staff_training_required": false,
    "review_date": null,
    "review_completed": false,
    "review_notes": null,
    "attachments": [],
    "priority": "medium",
    "requires_notification_to_cqc": true,
    "cqc_notification_sent": false,
    "cqc_notification_date": null,
    "cqc_reference": null,
    "police_involved": true,
    "police_reference": null,
    "confidential": false,
    "id": "696758d7766141f436713725",
    "created_date": "2026-01-14T08:50:31.650000",
    "updated_date": "2026-01-14T08:50:31.650000",
    "created_by_id": "69578dc85ffbccbf237c772e",
    "created_by": "mobappssolutions169@gmail.com",
    "is_sample": false
  },
  {
    "incident_reference": "INC-20251118-0002",
    "incident_type": "injury",
    "sub_category": null,
    "severity": "medium",
    "is_safeguarding_concern": false,
    "safeguarding_type": [],
    "client_id": "6909e7f22522fdf33fb86ec7",
    "staff_id": "",
    "reported_by_staff_id": "690d9c240a34ca4023dc316e",
    "visit_id": null,
    "incident_date": "2025-11-18T18:00",
    "reported_date": "2025-11-18T13:13:33.551Z",
    "discovery_date": null,
    "location": "Aries House, 60 Garmoyle Road, Liverpool",
    "location_detail": "Aries House, 60 Garmoyle Road, Liverpool, L15 3JH",
    "description": "John injured ",
    "what_happened": "",
    "immediate_action_taken": "Hospital ",
    "injury_details": null,
    "witnesses": [],
    "family_notified": false,
    "family_notification_date": null,
    "family_notification_method": null,
    "family_notified_by": null,
    "authorities_notified": [],
    "status": "reported",
    "investigation": null,
    "outcome": null,
    "resolution_notes": null,
    "resolved_by": null,
    "resolved_date": null,
    "lessons_learned": null,
    "preventive_measures": [],
    "risk_assessment_updated": false,
    "care_plan_updated": false,
    "staff_training_required": false,
    "review_date": null,
    "review_completed": false,
    "review_notes": null,
    "attachments": [],
    "priority": "medium",
    "requires_notification_to_cqc": false,
    "cqc_notification_sent": false,
    "cqc_notification_date": null,
    "cqc_reference": null,
    "police_involved": false,
    "police_reference": null,
    "confidential": false,
    "id": "691c70fb02dcecf02020cf1a",
    "created_date": "2025-11-18T13:13:31.959000",
    "updated_date": "2025-11-18T13:13:31.959000",
    "created_by_id": "690d9c240a34ca4023dc316e",
    "created_by": "vipin@appsandwebdevelopmentsolutions.com",
    "is_sample": false
  },
  {
    "incident_reference": "INC-20251107-0001",
    "incident_type": "injury",
    "sub_category": null,
    "severity": "high",
    "is_safeguarding_concern": true,
    "safeguarding_type": [
      "self_neglect"
    ],
    "client_id": "6909eb743d50d37c98f3e451",
    "staff_id": "",
    "reported_by_staff_id": "6909d012185f56ea55d9e5a3",
    "visit_id": null,
    "incident_date": "2025-11-07T10:07",
    "reported_date": "2025-11-07T10:08:30.583Z",
    "discovery_date": null,
    "location": "Kitchen",
    "location_detail": "test",
    "description": "Test",
    "what_happened": "",
    "immediate_action_taken": "Hospital",
    "injury_details": null,
    "witnesses": [],
    "family_notified": true,
    "family_notification_date": null,
    "family_notification_method": null,
    "family_notified_by": null,
    "authorities_notified": [],
    "status": "resolved",
    "investigation": {
      "investigator_staff_id": null,
      "investigation_start_date": null,
      "investigation_completion_date": null,
      "findings": "iugdiusg",
      "root_cause": null,
      "contributing_factors": []
    },
    "outcome": null,
    "resolution_notes": "today 13 11 25",
    "resolved_by": null,
    "resolved_date": null,
    "lessons_learned": "Test",
    "preventive_measures": [],
    "risk_assessment_updated": false,
    "care_plan_updated": false,
    "staff_training_required": false,
    "review_date": null,
    "review_completed": false,
    "review_notes": null,
    "attachments": [],
    "priority": "medium",
    "requires_notification_to_cqc": true,
    "cqc_notification_sent": false,
    "cqc_notification_date": null,
    "cqc_reference": null,
    "police_involved": false,
    "police_reference": null,
    "confidential": false,
    "id": "690dc51df5a6e5b7cc8d8fa2",
    "created_date": "2025-11-07T10:08:29.170000",
    "updated_date": "2025-11-13T12:18:44.566000",
    "created_by_id": "6909d012185f56ea55d9e5a3",
    "created_by": "m.carter@omegalife.uk",
    "is_sample": false
  }
]