[
  {
    "family_aware": null,
    "mobility_level": "Moderate",
    "night_considerations": null,
    "assembly_point": null,
    "critical_equipment": [],
    "alternative_exit": null,
    "client_id": "694146c3b47d88b4898e0e0d",
    "evacuation_method": "Assisted walking",
    "practice_evacuations": [],
    "refuge_area_location": null,
    "hearing": null,
    "communication": null,
    "client_involved": null,
    "location_in_building": null,
    "ability_to_respond_to_alarm": null,
    "special_instructions": null,
    "nearest_exit": null,
    "refuge_area_option": null,
    "equipment_required": [],
    "assessed_by": "vipin@appsandwebdevelopmentsolutions.com",
    "vision": null,
    "review_date": null,
    "cognitive_awareness": null,
    "staff_required": null,
    "medication_grab_bag": null,
    "assessment_date": "2026-03-30",
    "status": "active",
    "id": "69ca1824236a36303f11630a",
    "created_date": "2026-03-30T06:28:52.579000",
    "updated_date": "2026-03-30T06:28:52.579000",
    "created_by_id": "690d9c240a34ca4023dc316e",
    "created_by": "vipin@appsandwebdevelopmentsolutions.com",
    "is_sample": false
  },
  {
    "client_id": "6909e7f22522fdf33fb86ec6",
    "assessment_date": "2026-01-14",
    "assessed_by": "m.carter@omegalife.uk",
    "review_date": null,
    "mobility_level": "Mobilises short distances with wheeled walking frame; unable to manage stairs.",
    "hearing": null,
    "vision": null,
    "communication": null,
    "cognitive_awareness": null,
    "ability_to_respond_to_alarm": null,
    "location_in_building": null,
    "nearest_exit": null,
    "alternative_exit": null,
    "evacuation_method": "Aided evacuation with wheeled walking frame.",
    "staff_required": null,
    "equipment_required": [],
    "assembly_point": null,
    "special_instructions": null,
    "refuge_area_option": null,
    "refuge_area_location": null,
    "night_considerations": null,
    "medication_grab_bag": null,
    "critical_equipment": [],
    "practice_evacuations": [],
    "family_aware": null,
    "client_involved": null,
    "status": "active",
    "id": "69677e10b65daa0f89cdc747",
    "created_date": "2026-01-14T11:29:20.951000",
    "updated_date": "2026-01-14T11:29:20.951000",
    "created_by_id": "6909d012185f56ea55d9e5a3",
    "created_by": "m.carter@omegalife.uk",
    "is_sample": false
  },
  {
    "client_id": "6909e7f22522fdf33fb86ec6",
    "assessment_date": "2026-01-14",
    "assessed_by": "m.carter@omegalife.uk",
    "review_date": null,
    "mobility_level": "Mobilises short distances with a wheeled walking frame; unable to manage stairs safely.",
    "hearing": null,
    "vision": null,
    "communication": null,
    "cognitive_awareness": null,
    "ability_to_respond_to_alarm": null,
    "location_in_building": null,
    "nearest_exit": null,
    "alternative_exit": null,
    "evacuation_method": "Assisted evacuation via stairs; independent on level ground with walking aid.",
    "staff_required": null,
    "equipment_required": [],
    "assembly_point": null,
    "special_instructions": null,
    "refuge_area_option": null,
    "refuge_area_location": null,
    "night_considerations": null,
    "medication_grab_bag": null,
    "critical_equipment": [],
    "practice_evacuations": [],
    "family_aware": null,
    "client_involved": null,
    "status": "active",
    "id": "69676803df8bcbe3393f5259",
    "created_date": "2026-01-14T09:55:15.996000",
    "updated_date": "2026-01-14T09:55:15.996000",
    "created_by_id": "6909d012185f56ea55d9e5a3",
    "created_by": "m.carter@omegalife.uk",
    "is_sample": false
  },
  {
    "client_id": "6909e7f22522fdf33fb86ec6",
    "assessment_date": "2026-01-14",
    "assessed_by": "m.carter@omegalife.uk",
    "review_date": null,
    "mobility_level": "Mobilises short distances with a wheeled walking frame; unable to manage stairs.",
    "hearing": null,
    "vision": null,
    "communication": null,
    "cognitive_awareness": null,
    "ability_to_respond_to_alarm": null,
    "location_in_building": null,
    "nearest_exit": null,
    "alternative_exit": null,
    "evacuation_method": "Assisted evacuation via walking frame or wheelchair.",
    "staff_required": null,
    "equipment_required": [],
    "assembly_point": null,
    "special_instructions": null,
    "refuge_area_option": null,
    "refuge_area_location": null,
    "night_considerations": null,
    "medication_grab_bag": null,
    "critical_equipment": [],
    "practice_evacuations": [],
    "family_aware": null,
    "client_involved": null,
    "status": "active",
    "id": "6967668d4e47fcba4ef9612c",
    "created_date": "2026-01-14T09:49:01.411000",
    "updated_date": "2026-01-14T09:49:01.411000",
    "created_by_id": "6909d012185f56ea55d9e5a3",
    "created_by": "m.carter@omegalife.uk",
    "is_sample": false
  },
  {
    "client_id": "694146c3b47d88b4898e0e0d",
    "assessment_date": "2025-12-16",
    "assessed_by": "AI Import",
    "review_date": "2026-03-16",
    "mobility_level": "fully_mobile",
    "hearing": null,
    "vision": null,
    "communication": null,
    "cognitive_awareness": null,
    "ability_to_respond_to_alarm": null,
    "location_in_building": null,
    "nearest_exit": null,
    "alternative_exit": null,
    "evacuation_method": "with_physical_assistance",
    "staff_required": 1,
    "equipment_required": [],
    "assembly_point": "",
    "special_instructions": "",
    "refuge_area_option": null,
    "refuge_area_location": null,
    "night_considerations": null,
    "medication_grab_bag": null,
    "critical_equipment": [],
    "practice_evacuations": [],
    "family_aware": null,
    "client_involved": null,
    "status": "active",
    "id": "694146cba9b5672cb806365e",
    "created_date": "2025-12-16T11:47:23.658000",
    "updated_date": "2025-12-16T11:47:23.658000",
    "created_by_id": "6909e61b89f26ef7fa768434",
    "created_by": "p.holt@omegalife.uk",
    "is_sample": false
  },
  {
    "client_id": "69412e1429f3d1b18f985498",
    "assessment_date": "2025-12-16",
    "assessed_by": "AI Import",
    "review_date": "2026-03-16",
    "mobility_level": "slow_mobility",
    "hearing": null,
    "vision": null,
    "communication": null,
    "cognitive_awareness": null,
    "ability_to_respond_to_alarm": null,
    "location_in_building": null,
    "nearest_exit": null,
    "alternative_exit": null,
    "evacuation_method": "with_physical_assistance",
    "staff_required": 1,
    "equipment_required": [
      "Wheeled Zimmer frame"
    ],
    "assembly_point": "",
    "special_instructions": "Ensure clear walkways.",
    "refuge_area_option": null,
    "refuge_area_location": null,
    "night_considerations": null,
    "medication_grab_bag": null,
    "critical_equipment": [],
    "practice_evacuations": [],
    "family_aware": null,
    "client_involved": null,
    "status": "active",
    "id": "69412e1b5a66842b5558c921",
    "created_date": "2025-12-16T10:02:03.112000",
    "updated_date": "2025-12-16T10:02:03.112000",
    "created_by_id": "6909e61b89f26ef7fa768434",
    "created_by": "p.holt@omegalife.uk",
    "is_sample": false
  },
  {
    "client_id": "692f03f12961d743e9f36465",
    "assessment_date": "2025-12-02",
    "assessed_by": "AI Import",
    "review_date": "2026-03-02",
    "mobility_level": "fully_mobile",
    "hearing": null,
    "vision": null,
    "communication": null,
    "cognitive_awareness": null,
    "ability_to_respond_to_alarm": null,
    "location_in_building": null,
    "nearest_exit": null,
    "alternative_exit": null,
    "evacuation_method": "with_physical_assistance",
    "staff_required": 1,
    "equipment_required": [],
    "assembly_point": "N/A",
    "special_instructions": "N/A",
    "refuge_area_option": null,
    "refuge_area_location": null,
    "night_considerations": null,
    "medication_grab_bag": null,
    "critical_equipment": [],
    "practice_evacuations": [],
    "family_aware": null,
    "client_involved": null,
    "status": "active",
    "id": "692f03f7dd771f90de357947",
    "created_date": "2025-12-02T15:21:27.766000",
    "updated_date": "2025-12-02T15:21:27.766000",
    "created_by_id": "6909e61b89f26ef7fa768434",
    "created_by": "p.holt@omegalife.uk",
    "is_sample": false
  },
  {
    "client_id": "6914b519444801b5d13b928d",
    "assessment_date": "2025-01-05",
    "assessed_by": "John Matthews (self) with Michael Chen",
    "review_date": "2025-07-05",
    "mobility_level": "wheelchair_independent",
    "hearing": {
      "hearing_impaired": false,
      "hearing_aid": false,
      "details": "Hearing normal"
    },
    "vision": {
      "visual_impairment": false,
      "glasses": false,
      "guide_dog": false,
      "details": "Vision normal"
    },
    "communication": {
      "verbal": true,
      "sign_language": false,
      "communication_aids": [
        "Mobile phone"
      ],
      "details": "Fully able to communicate. Has emergency pendant alarm"
    },
    "cognitive_awareness": "fully_aware",
    "ability_to_respond_to_alarm": "independently",
    "location_in_building": "Ground floor flat, no stairs required",
    "nearest_exit": "Front door - flat entrance",
    "alternative_exit": "Patio doors to garden (level access)",
    "evacuation_method": "with_supervision",
    "staff_required": 0,
    "equipment_required": [
      "Powered wheelchair (if charged)",
      "Mobile phone"
    ],
    "assembly_point": "Street outside property, near lamppost",
    "special_instructions": "John is fully capable of self-evacuation in powered wheelchair. Flat is ground floor with level access. In event of fire, John will exit via front door or patio doors independently. Emergency pendant alarm will alert response team",
    "refuge_area_option": false,
    "refuge_area_location": null,
    "night_considerations": "Wheelchair parked next to bed for easy transfer. Mobile phone and pendant alarm on bedside table. John can transfer independently to wheelchair",
    "medication_grab_bag": false,
    "critical_equipment": [
      "Wheelchair",
      "Mobile phone",
      "Emergency pendant"
    ],
    "practice_evacuations": [
      {
        "date": "2025-01-05",
        "successful": true,
        "time_taken": "1 minute 30 seconds",
        "notes": "John evacuated independently via front door in powered wheelchair. Very capable"
      }
    ],
    "family_aware": false,
    "client_involved": true,
    "status": "active",
    "id": "69149eb41e62625d34254b68",
    "created_date": "2025-11-12T14:50:28.602000",
    "updated_date": "2025-11-12T16:31:40.434000",
    "created_by_id": "6909d012185f56ea55d9e5a3",
    "created_by": "m.carter@omegalife.uk",
    "is_sample": false
  },
  {
    "client_id": "6914b519444801b5d13b928e",
    "assessment_date": "2025-01-10",
    "assessed_by": "Emma Williams",
    "review_date": "2025-07-10",
    "mobility_level": "fully_mobile",
    "hearing": {
      "hearing_impaired": false,
      "hearing_aid": false,
      "details": "Hearing good"
    },
    "vision": {
      "visual_impairment": false,
      "glasses": false,
      "guide_dog": false,
      "details": "Vision normal"
    },
    "communication": {
      "verbal": true,
      "sign_language": false,
      "communication_aids": [
        "Visual fire safety card"
      ],
      "details": "Verbal communication good. Benefits from visual reminders"
    },
    "cognitive_awareness": "fully_aware",
    "ability_to_respond_to_alarm": "independently",
    "location_in_building": "Flat 3, First Floor",
    "nearest_exit": "Main stairwell - turn right out of flat",
    "alternative_exit": "Fire escape at end of corridor",
    "evacuation_method": "with_supervision",
    "staff_required": 1,
    "equipment_required": [
      "Visual fire procedure card",
      "Coat",
      "Phone"
    ],
    "assembly_point": "Car park, by the bins",
    "special_instructions": "Danny knows fire procedure and can evacuate independently. However, may benefit from staff supervision to ensure he follows procedure calmly. Has practiced evacuation multiple times. Visual fire card kept by front door",
    "refuge_area_option": false,
    "refuge_area_location": null,
    "night_considerations": "Visual fire procedure card has glow-in-dark elements. Danny knows to take phone and keys. May need reassurance if fire alarm sounds at night",
    "medication_grab_bag": true,
    "critical_equipment": [
      "Phone",
      "Keys",
      "Visual fire card"
    ],
    "practice_evacuations": [
      {
        "date": "2024-09-20",
        "successful": true,
        "time_taken": "2 minutes",
        "notes": "Danny followed procedure perfectly. Remembered to take phone and keys. Was calm throughout"
      },
      {
        "date": "2024-12-10",
        "successful": true,
        "time_taken": "1 minute 45 seconds",
        "notes": "Unannounced practice. Danny heard alarm, checked visual card, evacuated calmly. Excellent"
      }
    ],
    "family_aware": true,
    "client_involved": true,
    "status": "active",
    "id": "69149eb41e62625d34254b69",
    "created_date": "2025-11-12T14:50:28.602000",
    "updated_date": "2025-11-12T16:31:38.874000",
    "created_by_id": "6909d012185f56ea55d9e5a3",
    "created_by": "m.carter@omegalife.uk",
    "is_sample": false
  },
  {
    "client_id": "6914b519444801b5d13b928c",
    "assessment_date": "2024-12-15",
    "assessed_by": "David Thompson - Fire Safety Officer",
    "review_date": "2025-06-15",
    "mobility_level": "walking_aid",
    "hearing": {
      "hearing_impaired": false,
      "hearing_aid": false,
      "details": "Hearing good"
    },
    "vision": {
      "visual_impairment": false,
      "glasses": true,
      "guide_dog": false,
      "details": "Wears glasses for reading"
    },
    "communication": {
      "verbal": true,
      "sign_language": false,
      "communication_aids": [],
      "details": "Communicates verbally. May be confused due to dementia"
    },
    "cognitive_awareness": "significant_impairment",
    "ability_to_respond_to_alarm": "requires_assistance",
    "location_in_building": "Room 12, Ground Floor, East Wing",
    "nearest_exit": "Fire Exit A - End of corridor (15 meters)",
    "alternative_exit": "Main entrance via lounge (25 meters)",
    "evacuation_method": "with_physical_assistance",
    "staff_required": 1,
    "equipment_required": [
      "Walking frame",
      "Warm blanket",
      "Slippers"
    ],
    "assembly_point": "Front car park area, near oak tree",
    "special_instructions": "Betty may become distressed and confused during evacuation. Use calm, reassuring voice. Ensure she has walking frame. May need physical guidance. Can manage stairs slowly with support if necessary",
    "refuge_area_option": false,
    "refuge_area_location": null,
    "night_considerations": "Ensure Betty has slippers and dressing gown. May be more confused at night. Walking frame must be next to bed",
    "medication_grab_bag": true,
    "critical_equipment": [
      "Walking frame",
      "Glasses"
    ],
    "practice_evacuations": [
      {
        "date": "2024-10-15",
        "successful": true,
        "time_taken": "3 minutes 20 seconds",
        "notes": "Betty cooperated well. Used walking frame. One staff member sufficient"
      }
    ],
    "family_aware": true,
    "client_involved": true,
    "status": "active",
    "id": "69149eb41e62625d34254b67",
    "created_date": "2025-11-12T14:50:28.602000",
    "updated_date": "2025-11-12T16:31:43.377000",
    "created_by_id": "6909d012185f56ea55d9e5a3",
    "created_by": "m.carter@omegalife.uk",
    "is_sample": false
  }
]